[
  {
    "description": "",
    "elements": [
      {
        "description": "",
        "id": "login-page-testcases;login-with-valid-userdetails",
        "keyword": "Scenario",
        "line": 3,
        "name": "Login with Valid userDetails",
        "steps": [
          {
            "keyword": "Before",
            "hidden": true,
            "result": {
              "status": "passed",
              "duration": 1116543200
            }
          },
          {
            "arguments": [],
            "keyword": "And ",
            "line": 5,
            "name": "I goto login page \"https://playground.bsparksoftwaretechnologies.com/login\"",
            "match": {
              "location": "src\\test\\stepsDefinitions\\login.step.ts:11"
            },
            "result": {
              "status": "passed",
              "duration": 575700499
            }
          },
          {
            "arguments": [],
            "keyword": "When ",
            "line": 6,
            "name": "I enter username \"jhon1@gmail.com\" and Password \"test@123\"",
            "match": {
              "location": "src\\test\\stepsDefinitions\\login.step.ts:17"
            },
            "result": {
              "status": "passed",
              "duration": 228152500
            }
          },
          {
            "arguments": [],
            "keyword": "And ",
            "line": 7,
            "name": "I Click login button",
            "match": {
              "location": "src\\test\\stepsDefinitions\\login.step.ts:23"
            },
            "result": {
              "status": "passed",
              "duration": 1164301099
            }
          },
          {
            "arguments": [],
            "keyword": "Then ",
            "line": 8,
            "name": "I Validate home page title \"Dashboard\"",
            "match": {
              "location": "src\\test\\stepsDefinitions\\login.step.ts:34"
            },
            "result": {
              "status": "passed",
              "duration": 333687599
            }
          },
          {
            "keyword": "After",
            "hidden": true,
            "result": {
              "status": "passed",
              "duration": 390525800
            }
          }
        ],
        "tags": [],
        "type": "scenario"
      }
    ],
    "id": "login-page-testcases",
    "line": 1,
    "keyword": "Feature",
    "name": "Login page testcases",
    "tags": [],
    "uri": "src\\test\\features\\login.feature"
  }
]